pymindwave2/__init__.py
pymindwave2/connector.py
pymindwave2/headset.py
pymindwave2/session.py
pymindwave2/utils/__init__.py
pymindwave2/utils/daemon_async.py
pymindwave2/utils/event_manager.py
pymindwave2/utils/logger.py
pymindwave2/utils/singleton_meta.py
pymindwave2/utils/stream_parser.py
pymindwave2-1.0.1.dist-info/LICENSE
pymindwave2-1.0.1.dist-info/METADATA
pymindwave2-1.0.1.dist-info/WHEEL
pymindwave2-1.0.1.dist-info/top_level.txt
pymindwave2-1.0.1.dist-info/RECORD
