Metadata-Version: 2.2
Name: pymindwave2
Version: 1.0.1
Summary: A Python package for seamless communication with Neurosky MindWave Mobile 2 headset.
Author-email: Ahmed Mohsen <ahmed25004@hotmail.com>
License: MIT
Project-URL: Homepage, https://github.com/PrinceEGY/pymindwave2
Project-URL: Issues, https://github.com/PrinceEGY/pymindwave2/issues
Project-URL: Documentation, https://princeegy.github.io/pymindwave2/
Keywords: bci,brain-computer interface,brainwaves,eeg,headset,mind control,mindwave,mindwave mobile,mindwave mobile 2,mindwavemobile,mindwavemobile2,motor imagery,neuroscience,neurosky
Classifier: License :: OSI Approved :: MIT License
Classifier: Programming Language :: Python :: 3.10
Classifier: Programming Language :: Python :: 3.11
Classifier: Programming Language :: Python :: 3.12
Classifier: Programming Language :: Python
Classifier: Operating System :: OS Independent
Classifier: Intended Audience :: Science/Research
Classifier: Intended Audience :: Education
Requires-Python: >=3.10
License-File: LICENSE
